etest/__init__.py
etest/test.py
namantest/__init__.py
namantest/__version__.py
namantest-0.0.1.dist-info/LICENSE
namantest-0.0.1.dist-info/METADATA
namantest-0.0.1.dist-info/WHEEL
namantest-0.0.1.dist-info/top_level.txt
namantest-0.0.1.dist-info/RECORD
